{
  "status": "success",
  "data": {
    "sector": "食品饮料",
    "stocks": [
      {
        "ts_code": "601274.SH",
        "name": "食品A股份",
        "in_date": "20230908"
      },
      {
        "ts_code": "006758.SZ",
        "name": "食品B公司",
        "in_date": "20220923"
      },
      {
        "ts_code": "607830.SH",
        "name": "食品C公司",
        "in_date": "20240407"
      },
      {
        "ts_code": "009997.SZ",
        "name": "食品D公司",
        "in_date": "20241024"
      },
      {
        "ts_code": "605598.SH",
        "name": "食品E集团",
        "in_date": "20230705"
      },
      {
        "ts_code": "008142.SZ",
        "name": "食品F公司",
        "in_date": "20241219"
      },
      {
        "ts_code": "606028.SH",
        "name": "食品G集团",
        "in_date": "20220916"
      },
      {
        "ts_code": "008405.SZ",
        "name": "食品H科技",
        "in_date": "20230717"
      },
      {
        "ts_code": "607699.SH",
        "name": "食品I股份",
        "in_date": "20221208"
      },
      {
        "ts_code": "009831.SZ",
        "name": "食品J公司",
        "in_date": "20241012"
      },
      {
        "ts_code": "608134.SH",
        "name": "食品K公司",
        "in_date": "20240430"
      },
      {
        "ts_code": "005784.SZ",
        "name": "食品L股份",
        "in_date": "20240417"
      },
      {
        "ts_code": "602045.SH",
        "name": "食品M股份",
        "in_date": "20241124"
      },
      {
        "ts_code": "001004.SZ",
        "name": "食品N股份",
        "in_date": "20230717"
      },
      {
        "ts_code": "606190.SH",
        "name": "食品O股份",
        "in_date": "20230623"
      },
      {
        "ts_code": "008773.SZ",
        "name": "食品P集团",
        "in_date": "20230724"
      },
      {
        "ts_code": "607177.SH",
        "name": "食品Q集团",
        "in_date": "20230314"
      },
      {
        "ts_code": "001540.SZ",
        "name": "食品R科技",
        "in_date": "20220905"
      },
      {
        "ts_code": "607652.SH",
        "name": "食品S股份",
        "in_date": "20240126"
      },
      {
        "ts_code": "009286.SZ",
        "name": "食品T股份",
        "in_date": "20240411"
      },
      {
        "ts_code": "606176.SH",
        "name": "食品U公司",
        "in_date": "20230820"
      },
      {
        "ts_code": "002108.SZ",
        "name": "食品V科技",
        "in_date": "20230320"
      }
    ],
    "total": 22,
    "update_time": "2025-05-02 15:07:58"
  }
}